README.md
build_server_client.py
setup.py
build_server_client.egg-info/PKG-INFO
build_server_client.egg-info/SOURCES.txt
build_server_client.egg-info/dependency_links.txt
build_server_client.egg-info/entry_points.txt
build_server_client.egg-info/requires.txt
build_server_client.egg-info/top_level.txt